[
    {
    "model": "movie_service.castmember",
    "pk": 1,
    "fields": {
        "person": 11,
        "roles": [
            1
        ]
    }
},
    {
    "model": "movie_service.castmember",
    "pk": 2,
    "fields": {
        "person": 12,
        "roles": [
            2
        ]
    }
},
    {
    "model": "movie_service.castmember",
    "pk": 3,
    "fields": {
        "person": 13,
        "roles": [
            2
        ]
    }
},
    {
    "model": "movie_service.castmember",
    "pk": 4,
    "fields": {
        "person": 24,
        "roles": [
            1, 2
        ]
    }
},
    {
    "model": "movie_service.castmember",
    "pk": 5,
    "fields": {
        "person": 25,
        "roles": [
            2
        ]
    }
},
    {
    "model": "movie_service.castmember",
    "pk": 6,
    "fields": {
        "person": 36,
        "roles": [
            1, 2
        ]
    }
},
    {
    "model": "movie_service.castmember",
    "pk": 7,
    "fields": {
        "person": 37,
        "roles": [
            1, 2
        ]
    }
},
    {
    "model": "movie_service.castmember",
    "pk": 8,
    "fields": {
        "person": 38,
        "roles": [
            2
        ]
    }
},
    {
    "model": "movie_service.castmember",
    "pk": 9,
    "fields": {
        "person": 49,
        "roles": [
            1, 2
        ]
    }
},
    {
    "model": "movie_service.castmember",
    "pk": 10,
    "fields": {
        "person": 57,
        "roles": [
            1
        ]
    }
},
    {
    "model": "movie_service.castmember",
    "pk": 11,
    "fields": {
        "person": 58,
        "roles": [
            2
        ]
    }
},
    {
    "model": "movie_service.castmember",
    "pk": 12,
    "fields": {
        "person": 59,
        "roles": [
            2
        ]
    }
},
    {
    "model": "movie_service.castmember",
    "pk": 13,
    "fields": {
        "person": 62,
        "roles": [
            1, 2
        ]
    }
},
    {
    "model": "movie_service.castmember",
    "pk": 14,
    "fields": {
        "person": 63,
        "roles": [
            2
        ]
    }
},
    {
    "model": "movie_service.castmember",
    "pk": 15,
    "fields": {
        "person": 65,
        "roles": [
            1, 2
        ]
    }
},
    {
    "model": "movie_service.castmember",
    "pk": 16,
    "fields": {
        "person": 66,
        "roles": [
            2
        ]
    }
},
    {
    "model": "movie_service.castmember",
    "pk": 17,
    "fields": {
        "person": 68,
        "roles": [
            1, 2
        ]
    }
},
    {
    "model": "movie_service.castmember",
    "pk": 18,
    "fields": {
        "person": 69,
        "roles": [
            2
        ]
    }
},
    {
    "model": "movie_service.castmember",
    "pk": 19,
    "fields": {
        "person": 71,
        "roles": [
            1
        ]
    }
},
    {
    "model": "movie_service.castmember",
    "pk": 20,
    "fields": {
        "person": 72,
        "roles": [
            2
        ]
    }
},
    {
    "model": "movie_service.castmember",
    "pk": 21,
    "fields": {
        "person": 74,
        "roles": [
            1
        ]
    }
},
    {
    "model": "movie_service.castmember",
    "pk": 22,
    "fields": {
        "person": 75,
        "roles": [
            2
        ]
    }
},
    {
    "model": "movie_service.castmember",
    "pk": 23,
    "fields": {
        "person": 74,
        "roles": [
            1, 2
        ]
    }
},
    {
    "model": "movie_service.castmember",
    "pk": 24,
    "fields": {
        "person": 78,
        "roles": [
            2
        ]
    }
},
    {
    "model": "movie_service.castmember",
    "pk": 25,
    "fields": {
        "person": 81,
        "roles": [
            1, 2
        ]
    }
},
    {
    "model": "movie_service.castmember",
    "pk": 26,
    "fields": {
        "person": 82,
        "roles": [
            2
        ]
    }
},
    {
    "model": "movie_service.castmember",
    "pk": 27,
    "fields": {
        "person": 88,
        "roles": [
            1
        ]
    }
},
    {
    "model": "movie_service.castmember",
    "pk": 28,
    "fields": {
        "person": 93,
        "roles": [
            1
        ]
    }
},
    {
    "model": "movie_service.castmember",
    "pk": 29,
    "fields": {
        "person": 96,
        "roles": [
            1
        ]
    }
},
    {
    "model": "movie_service.castmember",
    "pk": 30,
    "fields": {
        "person": 98,
        "roles": [
            1
        ]
    }
},
    {
    "model": "movie_service.castmember",
    "pk": 31,
    "fields": {
        "person": 100,
        "roles": [
            1
        ]
    }
},
    {
    "model": "movie_service.castmember",
    "pk": 32,
    "fields": {
        "person": 103,
        "roles": [
            1
        ]
    }
},
    {
    "model": "movie_service.castmember",
    "pk": 33,
    "fields": {
        "person": 106,
        "roles": [
            1
        ]
    }
}
]
